MANIFEST.in
README.md
requirements.txt
setup.cfg
setup.py
versioneer.py
botcity/plugins/email/__init__.py
botcity/plugins/email/_version.py
botcity/plugins/email/plugin.py
botcity/plugins/email/servers_config.py
botcity/plugins/email/utils.py
botcity_email_plugin.egg-info/PKG-INFO
botcity_email_plugin.egg-info/SOURCES.txt
botcity_email_plugin.egg-info/dependency_links.txt
botcity_email_plugin.egg-info/requires.txt
botcity_email_plugin.egg-info/top_level.txt
tests/test_import.py