Metadata-Version: 2.4
Name: botcity-email-plugin
Version: 0.1.6
Home-page: https://bitbucket.org/botcitydev/bot-email-plugin-python.git
Requires-Python: >=3.7
Requires-Dist: imap-tools>=1.11.0
Dynamic: description
Dynamic: description-content-type
Dynamic: home-page
Dynamic: requires-dist
Dynamic: requires-python
